{
  "interactionModel": {
    "languageModel": {
      "intents": [
        {
          "name": "AMAZON.HelpIntent",
          "samples": [
            "hilf mir",
            "hilfe",
            "was kann ich sagen"
          ]
        },
        {
          "name": "AMAZON.CancelIntent",
          "samples": [
            "abbrechen",
            "nein danke"
          ]
        },
        {
          "name": "AMAZON.StopIntent",
          "samples": [
            "stopp",
            "beenden"
          ]
        },
        {
          "name": "AMAZON.FallbackIntent",
          "samples": []
        },
        {
          "slots": [],
          "name": "StartLessonIntent",
          "samples": [
            "starte lerneinheit",
            "starte die lerneinheit",
            "beginne die lerneinheit",
            "lass uns anfangen",
            "beginne mit der lerneinheit"
          ]
        },
        {
          "slots": [
            {
              "name": "Begriff",
              "type": "AMAZON.SearchQuery"
            }
          ],
          "name": "AskDefinitionIntent",
          "samples": [
            "sag mir was {Begriff} ist",
            "erkläre mir was {Begriff} ist",
            "was bedeutet {Begriff}",
            "erkläre {Begriff}",
            "ich habe {Begriff} nicht verstanden",
            "was heißt {Begriff}"
          ]
        },
        {
          "slots": [],
          "name": "StartQuizIntent",
          "samples": [
            "beginne das quiz",
            "frag mich ab",
            "starte das quiz",
            "ich will mit dem quiz anfangen",
            "quiz starten",
            "jetzt Fragen"
          ]
        },
        {
          "slots": [
            {
              "name": "Zahl",
              "type": "AMAZON.NUMBER"
            },
            {
              "name": "Antwort",
              "type": "AMAZON.SearchQuery"
            },
            {
              "name": "AntwortOption",
              "type": "answeroption"
            }
          ],
          "name": "AnswerIntent",
          "samples": [
            "antwort {Antwort}",
            "ich glaube {Antwort}",
            "ich nehme {Antwort}",
            "ich wähle {Antwort}",
            "die antwort ist {Antwort}",
            "antwort {AntwortOption}",
            "{AntwortOption}",
            "ich glaube es ist antwort {AntwortOption}",
            "ich glaube es ist {AntwortOption}",
            "es ist antwort {AntwortOption}",
            "das sollte {AntwortOption} sein",
            "das sollte {Zahl} sein",
            "ich glaube es ist {Antwort}",
            "ich glaube es ist {Zahl}",
            "das sollte {Antwort} sein",
            "es ist {Antwort}",
            "es ist antwort {Zahl}",
            "{Zahl}",
            "ist es {Zahl}",
            "ich nehme {Zahl}",
            "antwort {Zahl}"
          ]
        },
        {
          "slots": [],
          "name": "RepeatQuestionIntent",
          "samples": [
            "wiederhole das bitte",
            "kannst du die letzte frage nochmal wiederholen",
            "kannst du die frage bitte nochmal wiederholen",
            "kannst du das bitte nochmal wiederholen",
            "kannst du das bitte wiederholen",
            "wiederhole die frage",
            "nochmal bitte",
            "bitte die letzte frage nochmal"
          ]
        },
        {
          "slots": [
            {
              "name": "Thema",
              "type": "topic"
            }
          ],
          "name": "GetScoreIntent",
          "samples": [
            "wie viele punkte habe ich in {Thema}",
            "was ist mein punktestand in {Thema}",
            "was ist mein punktestand im thema {Thema}",
            "wie ist mein punktestand",
            "punktestand in {Thema}"
          ]
        },
        {
          "slots": [],
          "name": "RecommendationIntent",
          "samples": [
            "wie kann ich mich verbessern",
            "gib mir eine empfehlung wie ich das nächste mal weiter machen kann",
            "wie kann ich mich nächstes mal verbessern",
            "wie sollte ich nächstes mal weiter machen",
            "hast du eine empfehlung für mich für das nächste mal",
            "wie soll ich weitermachen",
            "was ist dein vorschlag für das nächste Mal"
          ]
        },
        {
          "name": "AMAZON.NavigateHomeIntent",
          "samples": []
        },
        {
          "slots": [],
          "name": "InstructionsIntent",
          "samples": [
            "wie kannst du mir helfen",
            "wie funktionierst du",
            "wie funktioniert alles",
            "anleitung"
          ]
        },
        {
          "slots": [
            {
              "name": "thema",
              "type": "topic"
            }
          ],
          "name": "ChooseTopicIntent",
          "samples": [
            "ich möchte das thema wechseln",
            "wechsel zu {thema}",
            "wechsel zu thema {thema}",
            "ich wähle thema {thema}",
            "ich möchte das thema {thema}",
            "starte mit {thema}",
            "{thema}",
            "ich möchte {thema}",
            "ich wähle {thema}"
          ]
        },
        {
          "slots": [],
          "name": "TellStoryIntent",
          "samples": [
            "beginne die story",
            "fang an mit der story",
            "starte die story",
            "fang an",
            "mach weiter"
          ]
        },
        {
          "name": "AMAZON.YesIntent",
          "samples": []
        },
        {
          "name": "AMAZON.NoIntent",
          "samples": []
        },
        {
          "slots": [],
          "name": "EndLearnSessionIntent",
          "samples": [
            "beende die einheit",
            "bitte beende die lerneinheit",
            "ich mag nicht mehr",
            "hör auf",
            "schluss",
            "ende",
            "ich möchte nicht mehr",
            "mach schluss für heute",
            "beende die lerneinheit"
          ]
        },
        {
          "slots": [],
          "name": "LevelInfoIntent",
          "samples": [
            "ändere die schwierigkeitsstufe",
            "ändere den schwierigkeitsgrad",
            "ich möchte den schwierigkeitsgrad ändern",
            "kann ich die schwierigkeitsstufe anpassen",
            "kann ich die schwierigkeitsstufe ändern",
            "erhöhe die schwierigkeitsstufe",
            "erhöhe den schwierigkeitsgrad",
            "ich möchte leichtere fragen",
            "ich möchte schwierigere fragen",
            "kann ich den schwierigkeitsgrad anpassen"
          ]
        }
      ],
      "types": [
        {
          "values": [
            {
              "name": {
                "value": "sprache"
              }
            },
            {
              "name": {
                "value": "geografie"
              }
            },
            {
              "name": {
                "value": "politik"
              }
            },
            {
              "name": {
                "value": "kunst"
              }
            },
            {
              "name": {
                "synonyms": [
                  "historie"
                ],
                "value": "geschichte"
              }
            },
            {
              "name": {
                "synonyms": [
                  "naturwissenschaften"
                ],
                "value": "wissenschaft"
              }
            }
          ],
          "name": "topic"
        },
        {
          "values": [
            {
              "name": {
                "value": "d"
              }
            },
            {
              "name": {
                "value": "c"
              }
            },
            {
              "name": {
                "value": "b"
              }
            },
            {
              "name": {
                "value": "a"
              }
            }
          ],
          "name": "answeroption"
        }
      ],
      "invocationName": "lb demo"
    }
  }
}
